django_contact_form-5.1.2.dist-info/METADATA
django_contact_form-5.1.2.dist-info/WHEEL
django_contact_form-5.1.2.dist-info/entry_points.txt
django_contact_form-5.1.2.dist-info/licenses/LICENSE
django_contact_form/__init__.py
django_contact_form/_akismet.py
django_contact_form/akismet_urls.py
django_contact_form/forms.py
django_contact_form/locale/da/LC_MESSAGES/django.mo
django_contact_form/locale/da/LC_MESSAGES/django.po
django_contact_form/locale/de/LC_MESSAGES/django.mo
django_contact_form/locale/de/LC_MESSAGES/django.po
django_contact_form/locale/en/LC_MESSAGES/django.mo
django_contact_form/locale/en/LC_MESSAGES/django.po
django_contact_form/locale/es/LC_MESSAGES/django.mo
django_contact_form/locale/es/LC_MESSAGES/django.po
django_contact_form/locale/eu/LC_MESSAGES/django.mo
django_contact_form/locale/eu/LC_MESSAGES/django.po
django_contact_form/locale/fr/LC_MESSAGES/django.mo
django_contact_form/locale/fr/LC_MESSAGES/django.po
django_contact_form/locale/it/LC_MESSAGES/django.mo
django_contact_form/locale/it/LC_MESSAGES/django.po
django_contact_form/locale/nl/LC_MESSAGES/django.mo
django_contact_form/locale/nl/LC_MESSAGES/django.po
django_contact_form/locale/uk/LC_MESSAGES/django.mo
django_contact_form/locale/uk/LC_MESSAGES/django.po
django_contact_form/urls.py
django_contact_form/views.py
django_contact_form-5.1.2.dist-info/RECORD
