Metadata-Version: 2.1
Name: django-contact-form
Version: 5.1.2
Summary: A generic contact-form application for Django.
Keywords: django,email,contact-form
Author: James Bennett
Maintainer: James Bennett
License: BSD-3-Clause
Classifier: Development Status :: 5 - Production/Stable
Classifier: Environment :: Web Environment
Classifier: Framework :: Django
Classifier: Framework :: Django :: 4.2
Classifier: Framework :: Django :: 5.0
Classifier: Framework :: Django :: 5.1
Classifier: Intended Audience :: Developers
Classifier: License :: OSI Approved :: BSD License
Classifier: Operating System :: OS Independent
Classifier: Programming Language :: Python
Classifier: Programming Language :: Python :: 3
Classifier: Programming Language :: Python :: 3.9
Classifier: Programming Language :: Python :: 3.10
Classifier: Programming Language :: Python :: 3.11
Classifier: Programming Language :: Python :: 3.12
Classifier: Programming Language :: Python :: 3.13
Classifier: Topic :: Utilities
Project-URL: Documentation, https://django-contact-form.readthedocs.io/
Project-URL: Source Code, https://github.com/ubernostrum/django-contact-form
Requires-Python: >=3.9
Requires-Dist: Django>=4.2
Provides-Extra: akismet
Requires-Dist: akismet>=24.5.0; extra == "akismet"
